birdnet_analyzer/__init__.py
birdnet_analyzer/audio.py
birdnet_analyzer/cli.py
birdnet_analyzer/config.py
birdnet_analyzer/eBird_taxonomy_codes_2024E.json
birdnet_analyzer/model.py
birdnet_analyzer/translate.py
birdnet_analyzer/utils.py
birdnet_analyzer/analyze/__init__.py
birdnet_analyzer/analyze/__main__.py
birdnet_analyzer/analyze/cli.py
birdnet_analyzer/analyze/core.py
birdnet_analyzer/analyze/utils.py
birdnet_analyzer/embeddings/__init__.py
birdnet_analyzer/embeddings/__main__.py
birdnet_analyzer/embeddings/cli.py
birdnet_analyzer/embeddings/core.py
birdnet_analyzer/embeddings/utils.py
birdnet_analyzer/evaluation/__init__.py
birdnet_analyzer/evaluation/__main__.py
birdnet_analyzer/evaluation/assessment/__init__.py
birdnet_analyzer/evaluation/assessment/metrics.py
birdnet_analyzer/evaluation/assessment/performance_assessor.py
birdnet_analyzer/evaluation/assessment/plotting.py
birdnet_analyzer/evaluation/preprocessing/__init__.py
birdnet_analyzer/evaluation/preprocessing/data_processor.py
birdnet_analyzer/evaluation/preprocessing/utils.py
birdnet_analyzer/gui/__init__.py
birdnet_analyzer/gui/__main__.py
birdnet_analyzer/gui/analysis.py
birdnet_analyzer/gui/embeddings.py
birdnet_analyzer/gui/evaluation.py
birdnet_analyzer/gui/localization.py
birdnet_analyzer/gui/multi_file.py
birdnet_analyzer/gui/review.py
birdnet_analyzer/gui/search.py
birdnet_analyzer/gui/segments.py
birdnet_analyzer/gui/settings.py
birdnet_analyzer/gui/single_file.py
birdnet_analyzer/gui/species.py
birdnet_analyzer/gui/train.py
birdnet_analyzer/gui/utils.py
birdnet_analyzer/gui/assets/arrow_down.svg
birdnet_analyzer/gui/assets/arrow_left.svg
birdnet_analyzer/gui/assets/arrow_right.svg
birdnet_analyzer/gui/assets/arrow_up.svg
birdnet_analyzer/gui/assets/gui.css
birdnet_analyzer/gui/assets/gui.js
birdnet_analyzer/gui/assets/img/birdnet-icon.ico
birdnet_analyzer/gui/assets/img/birdnet_logo.png
birdnet_analyzer/gui/assets/img/birdnet_logo_no_transparent.png
birdnet_analyzer-2.4.0.dist-info/licenses/LICENSE
birdnet_analyzer-2.4.0.dist-info/METADATA
birdnet_analyzer-2.4.0.dist-info/WHEEL
birdnet_analyzer-2.4.0.dist-info/entry_points.txt
birdnet_analyzer-2.4.0.dist-info/top_level.txt
birdnet_analyzer-2.4.0.dist-info/RECORD
