Metadata-Version: 2.4
Name: birdnet_analyzer
Version: 2.4.0
Summary: BirdNET analyzer for scientific audio data processing and bird classification.
Author: Stefan Kahl
Maintainer: Josef Haupt, Max Mauermann
License: MIT
Project-URL: Homepage, https://birdnet.cornell.edu/birdnet
Project-URL: Documentation, https://birdnet-team.github.io/BirdNET-Analyzer/
Project-URL: Repository, https://github.com/birdnet-team/BirdNET-Analyzer
Project-URL: Issues, https://github.com/birdnet-team/BirdNET-Analyzer/issues
Project-URL: Download, https://github.com/birdnet-team/BirdNET-Analyzer/releases/latest
Keywords: birdnet,birdnet-analyzer
Classifier: Programming Language :: Python :: 3
Classifier: Programming Language :: Python :: 3.11
Classifier: Programming Language :: Python :: 3.12
Classifier: Operating System :: OS Independent
Classifier: Topic :: Multimedia :: Sound/Audio :: Analysis
Classifier: Topic :: Scientific/Engineering
Classifier: Topic :: Scientific/Engineering :: Information Analysis
Classifier: Topic :: Scientific/Engineering :: Artificial Intelligence
Requires-Python: >=3.11
License-File: LICENSE
Requires-Dist: librosa>=0.11
Requires-Dist: resampy
Requires-Dist: tensorflow>=2.20
Requires-Dist: pyarrow>=22.0.0; platform_system == "Darwin"
Requires-Dist: tqdm
Requires-Dist: pandas
Requires-Dist: matplotlib
Requires-Dist: kagglehub
Provides-Extra: train
Requires-Dist: keras-tuner; extra == "train"
Provides-Extra: server
Requires-Dist: bottle; extra == "server"
Requires-Dist: requests; extra == "server"
Provides-Extra: gui
Requires-Dist: birdnet-analyzer[embeddings,train]; extra == "gui"
Requires-Dist: gradio>=5.46; extra == "gui"
Requires-Dist: pywebview>=6.0; extra == "gui"
Requires-Dist: pyobjc-framework-UniformTypeIdentifiers; platform_system == "Darwin" and extra == "gui"
Requires-Dist: plotly[express]; extra == "gui"
Requires-Dist: pywin32; platform_system == "Windows" and extra == "gui"
Requires-Dist: qtpy; platform_system == "Linux" and extra == "gui"
Requires-Dist: PyGObject; platform_system == "Linux" and extra == "gui"
Provides-Extra: embeddings
Requires-Dist: perch-hoplite>=0.1.1; extra == "embeddings"
Provides-Extra: all
Requires-Dist: birdnet-analyzer[gui,server]; extra == "all"
Provides-Extra: docs
Requires-Dist: sphinx; extra == "docs"
Requires-Dist: sphinx-rtd-theme; extra == "docs"
Requires-Dist: sphinx-argparse; extra == "docs"
Provides-Extra: tests
Requires-Dist: pytest; extra == "tests"
Requires-Dist: pytest-timeout; extra == "tests"
Requires-Dist: pytest-order; extra == "tests"
Provides-Extra: dev
Requires-Dist: birdnet_analyzer[tests]; extra == "dev"
Requires-Dist: birdnet_analyzer[docs]; extra == "dev"
Requires-Dist: ruff; extra == "dev"
Dynamic: license-file
